{"across": {"1": {"clue": "1. \"Attack!\"", "answer": "      ", "row": 0, "col": 0}, "7": {"clue": "7. They're often dipped in wasabis", "answer": "        ", "row": 0, "col": 7}, "15": {"clue": "15. Best at a buffet, say", "answer": "      ", "row": 1, "col": 0}, "16": {"clue": "16. Tabasco turnover", "answer": "        ", "row": 1, "col": 7}, "17": {"clue": "17. Camry competitor", "answer": "      ", "row": 2, "col": 0}, "18": {"clue": "18. ___ Brewster, \"Arsenic and Old Lace\" role", "answer": "        ", "row": 2, "col": 7}, "19": {"clue": "19. Classic Jag", "answer": "   ", "row": 3, "col": 0}, "20": {"clue": "20. Common street name", "answer": "   ", "row": 3, "col": 4}, "22": {"clue": "22. The French way?", "answer": "   ", "row": 3, "col": 8}, "23": {"clue": "23. Spanish pronoun", "answer": "   ", "row": 3, "col": 12}, "24": {"clue": "24. Competitor of Clark and Emerson in coll. athletics", "answer": "   ", "row": 4, "col": 2}, "26": {"clue": "26. Range wear?", "answer": "         ", "row": 4, "col": 6}, "29": {"clue": "29. \"Give me a break already!\"", "answer": "        ", "row": 5, "col": 0}, "32": {"clue": "32. Chat", "answer": "   ", "row": 5, "col": 9}, "33": {"clue": "33. Sacrifice, e.g.", "answer": "    ", "row": 6, "col": 0}, "34": {"clue": "34. Griffin who created \"Jeopardy!\"", "answer": "    ", "row": 6, "col": 5}, "36": {"clue": "36. Under cover?", "answer": "     ", "row": 6, "col": 10}, "40": {"clue": "40. Michael of \"Weekend Update\" on \"S.N.L.\"", "answer": "   ", "row": 7, "col": 0}, "41": {"clue": "41. Go for a quick cruise, say", "answer": "       ", "row": 7, "col": 4}, "43": {"clue": "43. One of 17 on a Monopoly board: Abbr.", "answer": "   ", "row": 7, "col": 12}, "44": {"clue": "44. Copycat's comment", "answer": "     ", "row": 8, "col": 0}, "46": {"clue": "46. ___-serif", "answer": "    ", "row": 8, "col": 6}, "47": {"clue": "47. Comment often after \"Hmm ...\"", "answer": "    ", "row": 8, "col": 11}, "48": {"clue": "48. Cricket club", "answer": "   ", "row": 9, "col": 3}, "50": {"clue": "50. Holds", "answer": "        ", "row": 9, "col": 7}, "52": {"clue": "52. Bosom buddies", "answer": "         ", "row": 10, "col": 0}, "56": {"clue": "56. Where the ball drops on New Year's Eve ... as depicted literally in four places in this puzzle", "answer": "   ", "row": 10, "col": 10}, "57": {"clue": "57. ___-eyed", "answer": "   ", "row": 11, "col": 0}, "58": {"clue": "58. Want-ad abbr.", "answer": "   ", "row": 11, "col": 4}, "59": {"clue": "59. Speed", "answer": "   ", "row": 11, "col": 8}, "61": {"clue": "61. California's ___ River", "answer": "   ", "row": 11, "col": 12}, "64": {"clue": "64. Bounding", "answer": "        ", "row": 12, "col": 0}, "67": {"clue": "67. One of the Brothers Karamazov", "answer": "      ", "row": 12, "col": 9}, "69": {"clue": "69. Brewed beverage", "answer": "        ", "row": 13, "col": 0}, "70": {"clue": "70. Laudanum, e.g.", "answer": "      ", "row": 13, "col": 9}, "71": {"clue": "71. Ran out on", "answer": "        ", "row": 14, "col": 0}, "72": {"clue": "72. Dirty", "answer": "      ", "row": 14, "col": 9}}, "down": {"1": {"clue": "1. Sweet-talk", "answer": "    ", "row": 0, "col": 0}, "2": {"clue": "2. Any Mr. Olympia", "answer": "    ", "row": 0, "col": 1}, "3": {"clue": "3. Went for", "answer": "         ", "row": 0, "col": 2}, "4": {"clue": "4. Big name in camping gear", "answer": "   ", "row": 0, "col": 3}, "5": {"clue": "5. Life starter", "answer": "      ", "row": 0, "col": 4}, "6": {"clue": "6. Library indexing abbr.", "answer": "    ", "row": 0, "col": 5}, "7": {"clue": "7. Part of a sch. year", "answer": "   ", "row": 0, "col": 7}, "8": {"clue": "8. 2006 million-selling Andrea Bocelli album", "answer": "     ", "row": 0, "col": 8}, "9": {"clue": "9. Out, in a way", "answer": "      ", "row": 0, "col": 9}, "10": {"clue": "10. Letters that are hard to read?", "answer": "        ", "row": 0, "col": 10}, "11": {"clue": "11. Pasta name ending", "answer": "   ", "row": 0, "col": 11}, "12": {"clue": "12. \"American Buffalo\" playwright", "answer": "     ", "row": 0, "col": 12}, "13": {"clue": "13. Cousin of \"exempli gratia\"", "answer": "     ", "row": 0, "col": 13}, "14": {"clue": "14. Singers Bareilles and Evans", "answer": "     ", "row": 0, "col": 14}, "21": {"clue": "21. Strolls", "answer": "      ", "row": 3, "col": 6}, "25": {"clue": "25. Paris's ___ Saint-Louis", "answer": "   ", "row": 4, "col": 3}, "27": {"clue": "27. Milan-based fashion house", "answer": "       ", "row": 4, "col": 7}, "28": {"clue": "28. Arabic \"son of\"", "answer": "   ", "row": 4, "col": 11}, "29": {"clue": "29. Tolkien's Gorbag and Bolg", "answer": "    ", "row": 5, "col": 0}, "30": {"clue": "30. Old Ritz rival", "answer": "    ", "row": 5, "col": 1}, "31": {"clue": "31. Org. backing Obamacare", "answer": "   ", "row": 5, "col": 5}, "35": {"clue": "35. Go poof", "answer": "      ", "row": 6, "col": 8}, "37": {"clue": "37. Lead, e.g.", "answer": "         ", "row": 6, "col": 12}, "38": {"clue": "38. First name in daredevilry", "answer": "    ", "row": 6, "col": 13}, "39": {"clue": "39. Odd couple?", "answer": "    ", "row": 6, "col": 14}, "41": {"clue": "41. Pipe measure", "answer": "        ", "row": 7, "col": 4}, "42": {"clue": "42. \"Was ___ passiert?\" (German \"What happened?\")", "answer": "   ", "row": 7, "col": 9}, "45": {"clue": "45. Strip of paper around a Japanese book", "answer": "   ", "row": 8, "col": 3}, "47": {"clue": "47. Uganda's ___ Amin", "answer": "   ", "row": 8, "col": 11}, "49": {"clue": "49. White Cloud Temple worshiper", "answer": "      ", "row": 9, "col": 5}, "51": {"clue": "51. \"Resume speed,\" musically", "answer": "      ", "row": 9, "col": 10}, "52": {"clue": "52. Lollygagged", "answer": "     ", "row": 10, "col": 0}, "53": {"clue": "53. Clue for a car mechanic", "answer": "     ", "row": 10, "col": 1}, "54": {"clue": "54. Some subs", "answer": "     ", "row": 10, "col": 2}, "55": {"clue": "55. Jittery", "answer": "     ", "row": 10, "col": 6}, "60": {"clue": "60. Merger agreements?", "answer": "    ", "row": 11, "col": 9}, "62": {"clue": "62. Designer who wrote \"Things I Remember\"", "answer": "    ", "row": 11, "col": 13}, "63": {"clue": "63. Wasn't veracious", "answer": "    ", "row": 11, "col": 14}, "65": {"clue": "65. Tick off", "answer": "   ", "row": 12, "col": 3}, "66": {"clue": "66. Prayer object", "answer": "   ", "row": 12, "col": 7}, "68": {"clue": "68. Trailer for \"Rocky\" or \"Rambo\"?", "answer": "   ", "row": 12, "col": 11}}}