{"across": {"1": {"clue": "1. Forefront", "answer": "VAN", "row": 0, "col": 0}, "4": {"clue": "4. Docile person", "answer": "LAMB", "row": 0, "col": 6}, "8": {"clue": "8. Type of history", "answer": "ORAL", "row": 0, "col": 11}, "12": {"clue": "12. In a line", "answer": "AROW", "row": 1, "col": 0}, "14": {"clue": "14. Place of an action, in law", "answer": "VENUE", "row": 1, "col": 5}, "15": {"clue": "15. A lot of money", "answer": "PILE", "row": 1, "col": 11}, "16": {"clue": "16. Tree native to the southern U.S.", "answer": "TITI", "row": 2, "col": 0}, "17": {"clue": "17. Concern of Soviet officials", "answer": "EMIGRATION", "row": 2, "col": 5}, "19": {"clue": "19. Atmospheric pollutant", "answer": "AEROSOL", "row": 3, "col": 1}, "21": {"clue": "21. Liqueur and condiment flavor", "answer": "ANISE", "row": 3, "col": 9}, "22": {"clue": "22. Birthplace of the limerick", "answer": "ERIN", "row": 4, "col": 3}, "23": {"clue": "23. Located at or in the ear", "answer": "OTIC", "row": 4, "col": 8}, "24": {"clue": "24. Insect-eating mammal of Madagascar", "answer": "TENREC", "row": 5, "col": 0}, "27": {"clue": "27. Washington Monument, e.g.", "answer": "OBELISK", "row": 5, "col": 7}, "30": {"clue": "30. Part of the psyche", "answer": "EGO", "row": 6, "col": 0}, "31": {"clue": "31. Caliban, to Prospero", "answer": "SLAVE", "row": 6, "col": 4}, "33": {"clue": "33. Jack Horner, for one", "answer": "EATER", "row": 6, "col": 10}, "35": {"clue": "35. Signs of Rialto success", "answer": "SROS", "row": 7, "col": 0}, "37": {"clue": "37. Rejoice", "answer": "EXULT", "row": 7, "col": 5}, "39": {"clue": "39. Captain in a Verne novel", "answer": "NEMO", "row": 7, "col": 11}, "40": {"clue": "40. Doctrine", "answer": "TENET", "row": 8, "col": 0}, "42": {"clue": "42. Epic of the Trojan War", "answer": "ILIAD", "row": 8, "col": 6}, "44": {"clue": "44. Like a teacher's pet", "answer": "APT", "row": 8, "col": 12}, "45": {"clue": "45. Able to withstand stress", "answer": "TENSILE", "row": 9, "col": 1}, "47": {"clue": "47. \"There is no ___ but life\": Ruskin", "answer": "WEALTH", "row": 9, "col": 9}, "49": {"clue": "49. Wood and coal derivatives", "answer": "TARS", "row": 10, "col": 3}, "50": {"clue": "50. Almost invisible biter", "answer": "GNAT", "row": 10, "col": 8}, "51": {"clue": "51. Blazing", "answer": "AFIRE", "row": 11, "col": 1}, "53": {"clue": "53. Mouth of a clam", "answer": "ORIFICE", "row": 11, "col": 7}, "56": {"clue": "56. G.I. sent elsewhere", "answer": "TRANSFEREE", "row": 12, "col": 0}, "58": {"clue": "58. Frat's next of kin", "answer": "DORM", "row": 12, "col": 11}, "60": {"clue": "60. Make goo-goo eyes", "answer": "OGLE", "row": 13, "col": 0}, "61": {"clue": "61. Complete", "answer": "UTTER", "row": 13, "col": 5}, "62": {"clue": "62. Beat out barely", "answer": "EDGE", "row": 13, "col": 11}, "63": {"clue": "63. Candidate's concern", "answer": "POLL", "row": 14, "col": 0}, "64": {"clue": "64. Word between stop and listen", "answer": "LOOK", "row": 14, "col": 5}, "65": {"clue": "65. The time of many billions of lives", "answer": "EON", "row": 14, "col": 12}}, "down": {"1": {"clue": "1. Wine vessel", "answer": "VAT", "row": 0, "col": 0}, "2": {"clue": "2. \"The Toreador Song,\" e.g.", "answer": "ARIA", "row": 0, "col": 1}, "3": {"clue": "3. Observe", "answer": "NOTE", "row": 0, "col": 2}, "4": {"clue": "4. Winning manager in 1978 World Series", "answer": "LEMON", "row": 0, "col": 6}, "5": {"clue": "5. Dye", "answer": "ANIL", "row": 0, "col": 7}, "6": {"clue": "6. Drinking utensil", "answer": "MUG", "row": 0, "col": 8}, "7": {"clue": "7. Criticize sharply", "answer": "BERATE", "row": 0, "col": 9}, "8": {"clue": "8. Spectacles are his specialty", "answer": "OPTICIAN", "row": 0, "col": 11}, "9": {"clue": "9. Social reformer: 1849\u20131914", "answer": "RIIS", "row": 0, "col": 12}, "10": {"clue": "10. Succulent plant", "answer": "ALOE", "row": 0, "col": 13}, "11": {"clue": "11. Author Deighton", "answer": "LEN", "row": 0, "col": 14}, "13": {"clue": "13. Building artisan", "answer": "WIRER", "row": 1, "col": 3}, "14": {"clue": "14. Blister", "answer": "VESICLE", "row": 1, "col": 5}, "18": {"clue": "18. Old-womanish", "answer": "ANILE", "row": 2, "col": 10}, "20": {"clue": "20. Ilmenite and chalcopyrite", "answer": "ORES", "row": 3, "col": 4}, "23": {"clue": "23. Printers' daggers", "answer": "OBELI", "row": 4, "col": 8}, "24": {"clue": "24. Acid ___", "answer": "TEST", "row": 5, "col": 0}, "25": {"clue": "25. Bird known for its valuable plumes", "answer": "EGRET", "row": 5, "col": 1}, "26": {"clue": "26. Caldwell's \"___ Hears\"", "answer": "NOONE", "row": 5, "col": 2}, "27": {"clue": "27. Part of a seed plant", "answer": "OVULE", "row": 5, "col": 7}, "28": {"clue": "28. Peculate", "answer": "STEAL", "row": 5, "col": 12}, "29": {"clue": "29. Trim", "answer": "KEMPT", "row": 5, "col": 13}, "32": {"clue": "32. Branch or leaf angles", "answer": "AXILS", "row": 6, "col": 6}, "34": {"clue": "34. He wrote \"Portnoy's Complaint\"", "answer": "ROTH", "row": 6, "col": 14}, "36": {"clue": "36. Possible watcher on the Rhine", "answer": "SENTINEL", "row": 7, "col": 3}, "38": {"clue": "38. More like a lion's pelt", "answer": "TAWNIER", "row": 7, "col": 9}, "41": {"clue": "41. Autocrats", "answer": "TSARS", "row": 8, "col": 4}, "43": {"clue": "43. Unwilling to listen", "answer": "DEAF", "row": 8, "col": 10}, "46": {"clue": "46. Angry", "answer": "IREFUL", "row": 9, "col": 5}, "48": {"clue": "48. \"There is ___ in the affairs of men . . . \"", "answer": "ATIDE", "row": 9, "col": 11}, "50": {"clue": "50. Socrates or Isocrates", "answer": "GREEK", "row": 10, "col": 8}, "51": {"clue": "51. Jason's ship", "answer": "ARGO", "row": 11, "col": 1}, "52": {"clue": "52. Collapse", "answer": "FALL", "row": 11, "col": 2}, "53": {"clue": "53. Hamlet's \"___ take arms . . . \"", "answer": "ORTO", "row": 11, "col": 7}, "54": {"clue": "54. Word with area or zip", "answer": "CODE", "row": 11, "col": 12}, "55": {"clue": "55. Hence, to Hadrian", "answer": "ERGO", "row": 11, "col": 13}, "56": {"clue": "56. Kind of billing", "answer": "TOP", "row": 12, "col": 0}, "57": {"clue": "57. Ike's post in W.W. II", "answer": "ETO", "row": 12, "col": 6}, "59": {"clue": "59. Pieces for Fischer", "answer": "MEN", "row": 12, "col": 14}}}