{"across": {"1": {"clue": "1. Box", "answer": "SPAR", "row": 0, "col": 0}, "5": {"clue": "5. A Celt", "answer": "GAEL", "row": 0, "col": 5}, "9": {"clue": "9. Coin originally called disme", "answer": "DIME", "row": 0, "col": 11}, "13": {"clue": "13. Scarlett O'Hara's home", "answer": "TARA", "row": 1, "col": 0}, "14": {"clue": "14. Old Norse poems", "answer": "RUNES", "row": 1, "col": 5}, "16": {"clue": "16. ___ of March", "answer": "IDES", "row": 1, "col": 11}, "17": {"clue": "17. Collar or jacket", "answer": "ETON", "row": 2, "col": 0}, "18": {"clue": "18. Unit or tract follower", "answer": "ARIAN", "row": 2, "col": 5}, "19": {"clue": "19. Melodies", "answer": "AIRS", "row": 2, "col": 11}, "20": {"clue": "20. Song from \"A Chorus Line\"", "answer": "WHATIDIDFORLOVE", "row": 3, "col": 0}, "23": {"clue": "23. Former French coin", "answer": "SOU", "row": 4, "col": 3}, "24": {"clue": "24. Public vehicle", "answer": "BUS", "row": 4, "col": 9}, "25": {"clue": "25. Sports enthusiast", "answer": "FAN", "row": 5, "col": 0}, "28": {"clue": "28. Caustic remark", "answer": "SARCASM", "row": 5, "col": 4}, "32": {"clue": "32. Depot on a RR", "answer": "STA", "row": 5, "col": 12}, "35": {"clue": "35. Greek god of war", "answer": "ARES", "row": 6, "col": 0}, "37": {"clue": "37. Saw or hammer", "answer": "TOOL", "row": 6, "col": 5}, "38": {"clue": "38. A Philippine island", "answer": "BATAN", "row": 6, "col": 10}, "40": {"clue": "40. Song identified with Ruth Etting", "answer": "LOVEMEORLEAVEME", "row": 7, "col": 0}, "43": {"clue": "43. Odor", "answer": "SMELL", "row": 8, "col": 0}, "44": {"clue": "44. British carbine", "answer": "STEN", "row": 8, "col": 6}, "45": {"clue": "45. Region", "answer": "AREA", "row": 8, "col": 11}, "46": {"clue": "46. Cereal spike", "answer": "EAR", "row": 9, "col": 0}, "47": {"clue": "47. Serves", "answer": "ATTENDS", "row": 9, "col": 4}, "50": {"clue": "50. Blunder", "answer": "ERR", "row": 9, "col": 12}, "51": {"clue": "51. Fruit drink", "answer": "ADE", "row": 10, "col": 3}, "52": {"clue": "52. Lubricant", "answer": "OIL", "row": 10, "col": 9}, "54": {"clue": "54. First popular song that won an Emmy", "answer": "LOVEANDMARRIAGE", "row": 11, "col": 0}, "63": {"clue": "63. Assert", "answer": "AVER", "row": 12, "col": 0}, "64": {"clue": "64. Stock-exchange memberships", "answer": "SEATS", "row": 12, "col": 5}, "65": {"clue": "65. Stumble", "answer": "TRIP", "row": 12, "col": 11}, "66": {"clue": "66. Start of Caesar's message", "answer": "VENI", "row": 13, "col": 0}, "67": {"clue": "67. Follow", "answer": "ENSUE", "row": 13, "col": 5}, "68": {"clue": "68. Ireland, to 5 Across", "answer": "EIRE", "row": 13, "col": 11}, "69": {"clue": "69. Poker stake", "answer": "ANTE", "row": 14, "col": 0}, "70": {"clue": "70. Despot", "answer": "TSAR", "row": 14, "col": 6}, "71": {"clue": "71. Rank", "answer": "RATE", "row": 14, "col": 11}}, "down": {"1": {"clue": "1. Fret", "answer": "STEW", "row": 0, "col": 0}, "2": {"clue": "2. Trail", "answer": "PATH", "row": 0, "col": 1}, "3": {"clue": "3. Venezuelan copper center", "answer": "AROA", "row": 0, "col": 2}, "4": {"clue": "4. Is in a rage", "answer": "RANTS", "row": 0, "col": 3}, "5": {"clue": "5. Receive a college degree", "answer": "GRADUATE", "row": 0, "col": 5}, "6": {"clue": "6. Gold: Comb. form", "answer": "AURI", "row": 0, "col": 6}, "7": {"clue": "7. Wife of Geraint", "answer": "ENID", "row": 0, "col": 7}, "8": {"clue": "8. Sheet of paper", "answer": "LEAF", "row": 0, "col": 8}, "9": {"clue": "9. Tunes in the radio", "answer": "DIALS", "row": 0, "col": 11}, "10": {"clue": "10. One's own: Comb. form", "answer": "IDIO", "row": 0, "col": 12}, "11": {"clue": "11. ___ Griffin, TV host", "answer": "MERV", "row": 0, "col": 13}, "12": {"clue": "12. To be, to Tiberius", "answer": "ESSE", "row": 0, "col": 14}, "15": {"clue": "15. Supercilious people", "answer": "SNOBS", "row": 1, "col": 9}, "21": {"clue": "21. Large Hawaiian hawks", "answer": "IOS", "row": 3, "col": 4}, "22": {"clue": "22. Cuban dance", "answer": "RUMBA", "row": 3, "col": 10}, "25": {"clue": "25. Not true", "answer": "FALSE", "row": 5, "col": 0}, "26": {"clue": "26. Fragrance", "answer": "AROMA", "row": 5, "col": 1}, "27": {"clue": "27. At no time", "answer": "NEVER", "row": 5, "col": 2}, "29": {"clue": "29. Perch", "answer": "ROOST", "row": 5, "col": 6}, "30": {"clue": "30. Dance dip in Spain", "answer": "CORTE", "row": 5, "col": 7}, "31": {"clue": "31. Ethan or Woody", "answer": "ALLEN", "row": 5, "col": 8}, "32": {"clue": "32. Cubic meter", "answer": "STERE", "row": 5, "col": 12}, "33": {"clue": "33. One who domesticates", "answer": "TAMER", "row": 5, "col": 13}, "34": {"clue": "34. Close to, in poesy", "answer": "ANEAR", "row": 5, "col": 14}, "36": {"clue": "36. Parisian's condiment", "answer": "SEL", "row": 6, "col": 3}, "39": {"clue": "39. Actress Gardner", "answer": "AVA", "row": 6, "col": 11}, "41": {"clue": "41. Rimsky-Korsakov opera", "answer": "MLADA", "row": 7, "col": 4}, "42": {"clue": "42. One who sanctions", "answer": "ENDORSER", "row": 7, "col": 9}, "48": {"clue": "48. Taut", "answer": "TENSE", "row": 9, "col": 5}, "49": {"clue": "49. Title Churchill had", "answer": "SIR", "row": 9, "col": 10}, "51": {"clue": "51. Eagle's nest", "answer": "AERIE", "row": 10, "col": 3}, "53": {"clue": "53. Metric liquid measure", "answer": "LITER", "row": 10, "col": 11}, "54": {"clue": "54. Molten rock", "answer": "LAVA", "row": 11, "col": 0}, "55": {"clue": "55. Hot spot", "answer": "OVEN", "row": 11, "col": 1}, "56": {"clue": "56. Air passage", "answer": "VENT", "row": 11, "col": 2}, "57": {"clue": "57. Disfigurement on a car", "answer": "DENT", "row": 11, "col": 6}, "58": {"clue": "58. Bulk", "answer": "MASS", "row": 11, "col": 7}, "59": {"clue": "59. Polynesian spirit", "answer": "ATUA", "row": 11, "col": 8}, "60": {"clue": "60. Operatic offering", "answer": "ARIA", "row": 11, "col": 12}, "61": {"clue": "61. Encircled", "answer": "GIRT", "row": 11, "col": 13}, "62": {"clue": "62. Fencing sword", "answer": "EPEE", "row": 11, "col": 14}}}