{"across": {"1": {"clue": "Served well", "answer": "ACED", "row": 0, "col": 0}, "5": {"clue": "Without ___ (religiously)", "answer": "FAIL", "row": 0, "col": 5}, "9": {"clue": "It has a facility with animals: Abbr.", "answer": "ASPCA", "row": 0, "col": 10}, "14": {"clue": "Nice figure", "answer": "SALEPRICE", "row": 1, "col": 0}, "16": {"clue": "Truffula Tree defender, with \"the\"", "answer": "LORAX", "row": 1, "col": 10}, "17": {"clue": "Red carpet events", "answer": "PREMIERES", "row": 2, "col": 0}, "18": {"clue": "Playwright Pirandello", "answer": "LUIGI", "row": 2, "col": 10}, "19": {"clue": "One of Darrow's clients", "answer": "SCOPES", "row": 3, "col": 1}, "20": {"clue": "Enters via osmosis", "answer": "SEEPSIN", "row": 3, "col": 8}, "22": {"clue": "Hunting companion, maybe", "answer": "SETTER", "row": 4, "col": 0}, "23": {"clue": "Uninteresting voice", "answer": "SINGSONG", "row": 4, "col": 7}, "24": {"clue": "Main ingredients in hasenpfeffer", "answer": "HARES", "row": 5, "col": 0}, "25": {"clue": "\"Don't give up!\"", "answer": "BESTRONG", "row": 5, "col": 6}, "26": {"clue": "Manufacturer of boxy cars", "answer": "OTIS", "row": 6, "col": 0}, "27": {"clue": "Friend of Harry and Ron", "answer": "HERMIONE", "row": 6, "col": 5}, "28": {"clue": "Isolated PC key", "answer": "ESC", "row": 7, "col": 0}, "29": {"clue": "Unilateral decision-makers", "answer": "DESPOTS", "row": 7, "col": 4}, "30": {"clue": "Excellent, slangily", "answer": "RAD", "row": 7, "col": 12}, "33": {"clue": "Frequent subject on \"Desperate Housewives\"", "answer": "ADULTERY", "row": 8, "col": 2}, "35": {"clue": "Empty bottles", "answer": "TOPE", "row": 8, "col": 11}, "36": {"clue": "Like some jewel cases", "answer": "SLIMLINE", "row": 9, "col": 1}, "37": {"clue": "Bygone players", "answer": "HIFIS", "row": 9, "col": 10}, "38": {"clue": "Wasted", "answer": "MISSPENT", "row": 10, "col": 0}, "39": {"clue": "\"Char-r-rge!\"", "answer": "BANZAI", "row": 10, "col": 9}, "40": {"clue": "Head set?", "answer": "ANTLERS", "row": 11, "col": 0}, "41": {"clue": "Lousy driver, say", "answer": "DUFFER", "row": 11, "col": 8}, "42": {"clue": "Imaginary surface coinciding with the earth's sea level", "answer": "GEOID", "row": 12, "col": 0}, "43": {"clue": "Alopecia sufferer's purchase", "answer": "HAIRTONIC", "row": 12, "col": 6}, "46": {"clue": "\"Donnie ___\" (2001 cult film)", "answer": "DARKO", "row": 13, "col": 0}, "47": {"clue": "Like gazebos, often", "answer": "OPENSIDED", "row": 13, "col": 6}, "48": {"clue": "Pitching staff?", "answer": "ADMEN", "row": 14, "col": 0}, "49": {"clue": "Communism battler, with \"the\"", "answer": "WEST", "row": 14, "col": 6}, "50": {"clue": "Miss", "answer": "LASS", "row": 14, "col": 11}}, "down": {"1": {"clue": "Deadly desert denizen", "answer": "ASP", "row": 0, "col": 0}, "2": {"clue": "They come with belts", "answer": "CARSEATS", "row": 0, "col": 1}, "3": {"clue": "Potential blackout cause", "answer": "ELECTRICALSTORM", "row": 0, "col": 2}, "4": {"clue": "Puts in a bad position?", "answer": "DEMOTES", "row": 0, "col": 3}, "5": {"clue": "Less reserved", "answer": "FREER", "row": 0, "col": 5}, "6": {"clue": "Show of superiority", "answer": "AIRS", "row": 0, "col": 6}, "7": {"clue": "Winter coat", "answer": "ICE", "row": 0, "col": 7}, "8": {"clue": "Central concept of minimalism", "answer": "LESSISMORE", "row": 0, "col": 8}, "9": {"clue": "Quick movements", "answer": "ALLEGROS", "row": 0, "col": 10}, "10": {"clue": "\"Come and get it!\"", "answer": "SOUPSON", "row": 0, "col": 11}, "11": {"clue": "1894 adventure novel, with \"The\"", "answer": "PRISONEROFZENDA", "row": 0, "col": 12}, "12": {"clue": "Putting away", "answer": "CAGING", "row": 0, "col": 13}, "13": {"clue": "Giving a pink slip", "answer": "AXING", "row": 0, "col": 14}, "15": {"clue": "Singer's gift, colloquially", "answer": "PIPES", "row": 1, "col": 4}, "21": {"clue": "Body", "answer": "ENTITY", "row": 3, "col": 9}, "22": {"clue": "Mule, e.g.", "answer": "SHOE", "row": 4, "col": 0}, "23": {"clue": "Midgard ___ (monster of Norse myth)", "answer": "SERPENT", "row": 4, "col": 7}, "25": {"clue": "Top dog", "answer": "BESTINSHOW", "row": 5, "col": 6}, "27": {"clue": "Author of \"Something Happened,\" 1974", "answer": "HELLER", "row": 6, "col": 5}, "29": {"clue": "Bad-mouthed", "answer": "DUMPEDON", "row": 7, "col": 4}, "31": {"clue": "Things getting a lot of buzz about them?", "answer": "APIARIES", "row": 7, "col": 13}, "32": {"clue": "Portrayer of TV's Ricky", "answer": "DESI", "row": 7, "col": 14}, "34": {"clue": "Find objectionable", "answer": "DISLIKE", "row": 8, "col": 3}, "35": {"clue": "Early phonograph cylinder covering", "answer": "TINFOIL", "row": 8, "col": 11}, "36": {"clue": "Musical O'Connor", "answer": "SINEAD", "row": 9, "col": 1}, "37": {"clue": "Swordsmen's grips", "answer": "HAFTS", "row": 9, "col": 10}, "38": {"clue": "One of the Gabor sisters", "answer": "MAGDA", "row": 10, "col": 0}, "39": {"clue": "Very well done", "answer": "BURNT", "row": 10, "col": 9}, "41": {"clue": "Conks out", "answer": "DIES", "row": 11, "col": 8}, "44": {"clue": "Caricature", "answer": "APE", "row": 12, "col": 7}, "45": {"clue": "Certain investments, for short", "answer": "CDS", "row": 12, "col": 14}}}