{"across": {"1": {"clue": "Plays a siren", "answer": "TEMPTS", "row": 0, "col": 0}, "7": {"clue": "Gold Coast, today", "answer": "GHANA", "row": 0, "col": 7}, "12": {"clue": "Meander", "answer": "ROAM", "row": 0, "col": 13}, "16": {"clue": "It's a plus in a bank acct.", "answer": "DEP", "row": 0, "col": 18}, "19": {"clue": "Noted landing site", "answer": "ARARAT", "row": 1, "col": 0}, "20": {"clue": "Player of the younger Cunningham on \"Happy Days\"", "answer": "MORAN", "row": 1, "col": 7}, "21": {"clue": "Mach3 predecessor", "answer": "ATRA", "row": 1, "col": 13}, "22": {"clue": "\"Yes, I'm a Witch\" singer, 1992", "answer": "ONO", "row": 1, "col": 18}, "23": {"clue": "___ Bay, 1898 battle site", "answer": "MANILA", "row": 2, "col": 0}, "24": {"clue": "Deliver", "answer": "ADMINISTER", "row": 2, "col": 7}, "26": {"clue": "They push things", "answer": "ADS", "row": 2, "col": 18}, "27": {"clue": "File folder, e.g.", "answer": "ICON", "row": 3, "col": 2}, "28": {"clue": "President who was 65-Across (1872)", "answer": "CALVINCOOLIDGE", "row": 3, "col": 7}, "30": {"clue": "Heads up", "answer": "ASCENDS", "row": 4, "col": 0}, "33": {"clue": "Capital of Denmark?", "answer": "DEE", "row": 4, "col": 8}, "34": {"clue": "Come to naught", "answer": "FAIL", "row": 4, "col": 12}, "35": {"clue": "Fermented honey drink", "answer": "MEAD", "row": 4, "col": 17}, "36": {"clue": "Where kips are cash", "answer": "LAOS", "row": 5, "col": 0}, "37": {"clue": "Observe, in the Bible", "answer": "SEEST", "row": 5, "col": 5}, "39": {"clue": "Presidential daughter who was 65-Across (1998)", "answer": "MALIAOBAMA", "row": 5, "col": 11}, "41": {"clue": "First National Leaguer with 500 home runs", "answer": "OTT", "row": 6, "col": 0}, "42": {"clue": "Act out", "answer": "MIME", "row": 6, "col": 4}, "43": {"clue": "Staff", "answer": "MAN", "row": 6, "col": 10}, "44": {"clue": "Some slippers", "answer": "MULES", "row": 6, "col": 16}, "45": {"clue": "Novelist who was 65-Across (1804)", "answer": "NATHANIELHAWTHORNE", "row": 7, "col": 0}, "52": {"clue": "Early computer", "answer": "ENIAC", "row": 8, "col": 0}, "53": {"clue": "Yevtushenko's \"Babi ___\"", "answer": "YAR", "row": 8, "col": 8}, "54": {"clue": "Red Cross supply", "answer": "SERA", "row": 8, "col": 12}, "55": {"clue": "Word with black or pack", "answer": "JET", "row": 8, "col": 18}, "58": {"clue": "\"The Haj\" author", "answer": "URIS", "row": 9, "col": 3}, "61": {"clue": "Long way to go?", "answer": "LIMO", "row": 9, "col": 8}, "63": {"clue": "Bill provider", "answer": "ATM", "row": 9, "col": 13}, "64": {"clue": "___ Valley, 2002 Winter Olympics venue", "answer": "DEER", "row": 9, "col": 17}, "65": {"clue": "See 28-, 39-, 45-, 83-, 95- and 107-Across", "answer": "BORNONTHEFOURTHOFJULY", "row": 10, "col": 0}, "71": {"clue": "Plenty", "answer": "ALOT", "row": 11, "col": 0}, "72": {"clue": "Sri Lankan export", "answer": "TEA", "row": 11, "col": 5}, "73": {"clue": "Film canine", "answer": "ASTA", "row": 11, "col": 9}, "74": {"clue": "\"This is dedicated to the ___ love\"", "answer": "ONEI", "row": 11, "col": 14}, "75": {"clue": "Wordsworth's \"solitary Tree\"", "answer": "YEW", "row": 12, "col": 0}, "76": {"clue": "Interpret", "answer": "READ", "row": 12, "col": 5}, "78": {"clue": "Article in Der Spiegel", "answer": "EIN", "row": 12, "col": 10}, "79": {"clue": "Sweater style", "answer": "VNECK", "row": 12, "col": 16}, "83": {"clue": "Team owner who was 65-Across (1930)", "answer": "GEORGESTEINBRENNER", "row": 13, "col": 3}, "89": {"clue": "Have ___ one's words", "answer": "TOEAT", "row": 14, "col": 0}, "92": {"clue": "Set-___", "answer": "TOS", "row": 14, "col": 8}, "93": {"clue": "Sierra Nevada, e.g.", "answer": "BEER", "row": 14, "col": 13}, "94": {"clue": "Building block, of sorts", "answer": "DNA", "row": 14, "col": 18}, "95": {"clue": "Columnist who was 65-Across (1918)", "answer": "ANNLANDERS", "row": 15, "col": 0}, "99": {"clue": "Powerful blows", "answer": "SWATS", "row": 15, "col": 11}, "101": {"clue": "Attire usually worn with slippers", "answer": "TUTU", "row": 15, "col": 17}, "102": {"clue": "\"Unfaithful\" co-star, 2002", "answer": "GERE", "row": 16, "col": 0}, "103": {"clue": "The final Mrs. Chaplin", "answer": "OONA", "row": 16, "col": 5}, "104": {"clue": "Economic stat.", "answer": "CPI", "row": 16, "col": 10}, "105": {"clue": "Initially", "answer": "ATFIRST", "row": 16, "col": 14}, "107": {"clue": "Literary critic who was 65-Across (1905)", "answer": "LIONELTRILLING", "row": 17, "col": 0}, "111": {"clue": "Michigan college", "answer": "ALMA", "row": 17, "col": 15}, "112": {"clue": "When sung five times, an Abba hit", "answer": "IDO", "row": 18, "col": 0}, "113": {"clue": "Electrical impulse conductor in the body", "answer": "MOTONEURON", "row": 18, "col": 4}, "114": {"clue": "Riffraff", "answer": "RABBLE", "row": 18, "col": 15}, "117": {"clue": "D.C. player", "answer": "NAT", "row": 19, "col": 0}, "118": {"clue": "Knightwear?", "answer": "MAIL", "row": 19, "col": 4}, "119": {"clue": "Maytag acquisition of 2001", "answer": "AMANA", "row": 19, "col": 9}, "120": {"clue": "And others, in a footnote", "answer": "ETALIA", "row": 19, "col": 15}, "121": {"clue": "Most of a figure eight", "answer": "ESS", "row": 20, "col": 0}, "122": {"clue": "Coolers", "answer": "ADES", "row": 20, "col": 4}, "123": {"clue": "Water balloon sound", "answer": "SPLAT", "row": 20, "col": 9}, "124": {"clue": "Out", "answer": "ASLEEP", "row": 20, "col": 15}}, "down": {"1": {"clue": "Tufted topper", "answer": "TAM", "row": 0, "col": 0}, "2": {"clue": "Chapter", "answer": "ERA", "row": 0, "col": 1}, "3": {"clue": "Some large tubes", "answer": "MANICOTTI", "row": 0, "col": 2}, "4": {"clue": "They might be inflated", "answer": "PRICES", "row": 0, "col": 3}, "5": {"clue": "Part of Tennyson's \"crooked hands\"", "answer": "TALON", "row": 0, "col": 4}, "6": {"clue": "Pinch-hits (for)", "answer": "STANDSIN", "row": 0, "col": 5}, "7": {"clue": "Former financing inits.", "answer": "GMAC", "row": 0, "col": 7}, "8": {"clue": "Wannabe surfers", "answer": "HODADS", "row": 0, "col": 8}, "9": {"clue": "Cove, e.g.", "answer": "ARMLET", "row": 0, "col": 9}, "10": {"clue": "Sucker-like", "answer": "NAIVE", "row": 0, "col": 10}, "11": {"clue": "Years at the Vatican", "answer": "ANNI", "row": 0, "col": 11}, "12": {"clue": "Wily sort", "answer": "RASCAL", "row": 0, "col": 13}, "13": {"clue": "10th-century Holy Roman emperor", "answer": "OTTOII", "row": 0, "col": 14}, "14": {"clue": "Iris part", "answer": "AREOLA", "row": 0, "col": 15}, "15": {"clue": "Clayey deposit", "answer": "MARL", "row": 0, "col": 16}, "16": {"clue": "Conclude negotiations successfully", "answer": "DOADEAL", "row": 0, "col": 18}, "17": {"clue": "Chess closing", "answer": "ENDGAME", "row": 0, "col": 19}, "18": {"clue": "Impersonated", "answer": "POSEDAS", "row": 0, "col": 20}, "25": {"clue": "Bundles of joy, so to speak", "answer": "INFANTS", "row": 2, "col": 12}, "29": {"clue": "Infuse", "answer": "IMBUE", "row": 3, "col": 17}, "30": {"clue": "\"Home ___\"", "answer": "ALONE", "row": 4, "col": 0}, "31": {"clue": "Lord of the Flies", "answer": "SATAN", "row": 4, "col": 1}, "32": {"clue": "Convoy component", "answer": "SEMI", "row": 4, "col": 6}, "38": {"clue": "Wide shoe spec", "answer": "EEE", "row": 5, "col": 7}, "39": {"clue": "Wide-open mouth", "answer": "MAW", "row": 5, "col": 11}, "40": {"clue": "Every, in an Rx", "answer": "OMN", "row": 5, "col": 16}, "42": {"clue": "Lens used for close-ups", "answer": "MACRO", "row": 6, "col": 4}, "43": {"clue": "New World monkeys", "answer": "MARMOSETS", "row": 6, "col": 10}, "46": {"clue": "Frequent", "answer": "HAUNT", "row": 7, "col": 3}, "47": {"clue": "Singer Lovett", "answer": "LYLE", "row": 7, "col": 8}, "48": {"clue": "City on the slopes of Mount Carmel", "answer": "HAIFA", "row": 7, "col": 9}, "49": {"clue": "What a thermometer measures", "answer": "HEAT", "row": 7, "col": 13}, "50": {"clue": "Garden chemical brand", "answer": "ORTHO", "row": 7, "col": 14}, "51": {"clue": "One of the Estevez brothers", "answer": "RAMON", "row": 7, "col": 15}, "55": {"clue": "French game", "answer": "JEU", "row": 8, "col": 18}, "56": {"clue": "Dish that may be smoked", "answer": "EEL", "row": 8, "col": 19}, "57": {"clue": "Adjudge", "answer": "TRY", "row": 8, "col": 20}, "59": {"clue": "Prelim", "answer": "INTRO", "row": 9, "col": 5}, "60": {"clue": "Range rover", "answer": "STEER", "row": 9, "col": 6}, "62": {"clue": "Certain belly button", "answer": "OUTIE", "row": 9, "col": 11}, "64": {"clue": "Magic lamp figure", "answer": "DJINN", "row": 9, "col": 17}, "65": {"clue": "Seabiscuit, for one", "answer": "BAY", "row": 10, "col": 0}, "66": {"clue": "Crowd shout", "answer": "OLE", "row": 10, "col": 1}, "67": {"clue": "Ticket datum", "answer": "ROW", "row": 10, "col": 2}, "68": {"clue": "Den ___, Nederland", "answer": "HAAG", "row": 10, "col": 7}, "69": {"clue": "Eastern royal", "answer": "RANI", "row": 10, "col": 12}, "70": {"clue": "What a thermometer may measure", "answer": "FEVER", "row": 10, "col": 16}, "77": {"clue": "Get off at a station", "answer": "DETRAIN", "row": 12, "col": 8}, "80": {"clue": "Like adversity, one hopes", "answer": "ENDURABLE", "row": 12, "col": 18}, "81": {"clue": "Mint products", "answer": "CENTS", "row": 12, "col": 19}, "82": {"clue": "Sausage topper", "answer": "KRAUT", "row": 12, "col": 20}, "83": {"clue": "Ancient Greek anatomist", "answer": "GALEN", "row": 13, "col": 3}, "84": {"clue": "Seventh chapter", "answer": "ETA", "row": 13, "col": 4}, "85": {"clue": "\"I'll send an ___ to the world\" (Police lyric)", "answer": "SOS", "row": 13, "col": 9}, "86": {"clue": "Bird's org.", "answer": "NBA", "row": 13, "col": 13}, "87": {"clue": "Kind of test", "answer": "BETA", "row": 13, "col": 14}, "88": {"clue": "Interstate sign", "answer": "RESTAREA", "row": 13, "col": 15}, "89": {"clue": "\"Good night, and good luck,\" e.g.", "answer": "TAGLINE", "row": 14, "col": 0}, "90": {"clue": "Six Nations tribe", "answer": "ONEIDAS", "row": 14, "col": 1}, "91": {"clue": "Becomes established", "answer": "ENROOTS", "row": 14, "col": 2}, "96": {"clue": "Like some mutual funds", "answer": "NOLOAD", "row": 15, "col": 5}, "97": {"clue": "West of Nashville", "answer": "DOTTIE", "row": 15, "col": 6}, "98": {"clue": "Registers", "answer": "ENROLS", "row": 15, "col": 7}, "99": {"clue": "Air show maneuver", "answer": "SPIRAL", "row": 15, "col": 11}, "100": {"clue": "Actress Ryder", "answer": "WINONA", "row": 15, "col": 12}, "101": {"clue": "Kettledrum", "answer": "TIMBAL", "row": 15, "col": 17}, "104": {"clue": "Opposite of break apart", "answer": "CLUMP", "row": 16, "col": 10}, "106": {"clue": "High-heels alternatives", "answer": "FLATS", "row": 16, "col": 16}, "108": {"clue": "Anarchist Goldman", "answer": "EMMA", "row": 17, "col": 4}, "109": {"clue": "Meadowlands", "answer": "LEAS", "row": 17, "col": 9}, "110": {"clue": "Punkie", "answer": "GNAT", "row": 17, "col": 13}, "115": {"clue": "\"The dog ate my homework,\" probably", "answer": "LIE", "row": 18, "col": 19}, "116": {"clue": "Literary inits.", "answer": "EAP", "row": 18, "col": 20}}}